kndxhz_tools/__init__.py
kndxhz_tools-0.3.dist-info/METADATA
kndxhz_tools-0.3.dist-info/WHEEL
kndxhz_tools-0.3.dist-info/top_level.txt
kndxhz_tools-0.3.dist-info/RECORD
