Metadata-Version: 2.4
Name: kndxhz_tools
Version: 0.3
Summary: 一个自用的工具集
Home-page: https://github.com/kndxhz/kndxhz_tools
Author: kndxhz
Author-email: kndxhz@163.com
Classifier: Programming Language :: Python :: 3
Classifier: License :: OSI Approved :: MIT License
Classifier: Operating System :: OS Independent
Requires-Python: >=3.8
Dynamic: author
Dynamic: author-email
Dynamic: classifier
Dynamic: description
Dynamic: description-content-type
Dynamic: home-page
Dynamic: requires-python
Dynamic: summary
